Workbook

Sheet Portada
B2: Prueba de Certificación - Excel con IA
B5: Proyecto aplicado: análisis de ventas y proyección del próximo trimestre
B8: Estudiante | C8: SAMUEL ARDILA
B11: Problema elegido | C11: Identificar la categoría líder y proyectar el mes con mayores ventas del próximo trimestre.
B13: Pregunta clave | C13: ¿En qué mes del próximo trimestre se proyectan mayores ventas y qué categoría lidera el acumulado?
B15: Herramientas usadas | C15: Excel (tablas, fórmulas, gráficos y validaciones) + IA complementaria para estructurar análisis y guion.

Sheet Datos_Raw
A1: Datos originales (antes de limpieza)
A2: Esta hoja contiene variaciones intencionales de mayúsculas, espacios y formato de texto para demostrar la limpieza en Excel.
A3: Fecha | B3: Mes | C3: Region_raw | D3: Categoria_raw | E3: Unidades_raw | F3: Precio_Unitario
A4: 45292 | B4: Enero 2024 | C4: NORTE | D4: TECNOLOGIA | E4: 17 | F4: 2600
A5: 45292 | B5: Enero 2024 | C5: NORTE | D5: HOGAR | E5: 21 | F5: 1500
A6: 45292 | B6: Enero 2024 | C6: norte | D6: OFICINA | E6: 19 | F6: 1100
A7: 45292 | B7: Enero 2024 | C7: SUR | D7: Tecnologia | E7: 14 | F7: 2600
A8: 45292 | B8: Enero 2024 | C8: SUR | D8: Hogar | E8: 18 | F8: 1500
A9: 45292 | B9: Enero 2024 | C9: sur | D9: Oficina | E9: 16 | F9: 1100
A10: 45323 | B10: Febrero 2024 | C10: Norte | D10: Tecnologia | E10: 19 | F10: 2600
A11: 45323 | B11: Febrero 2024 | C11: Norte | D11: Hogar | E11: 24 | F11: 1500
A12: 45323 | B12: Febrero 2024 | C12: Norte | D12: Oficina | E12: 21 | F12: 1100
A13: 45323 | B13: Febrero 2024 | C13: Sur | D13: tecnologia | E13: 16 | F13: 2600
A14: 45323 | B14: Febrero 2024 | C14: Sur | D14: hogar | E14: 20 | F14: 1500
A15: 45323 | B15: Febrero 2024 | C15: Sur | D15: oficina | E15: 18 | F15: 1100
... A75: 45627 | B75: Diciembre 2024 | C75: Sur | D75: oficina | E75: 33 | F75: 1100

Sheet Datos_Limpios
A1: Datos limpios y validados
A2: La limpieza se apoya en fórmulas para estandarizar texto, convertir cantidades y recalcular ventas.
A3: Fecha | B3: Año | C3: Mes | D3: Region | E3: Categoria | F3: Unidades | G3: Precio_Unitario | H3: Ventas | I3: Estado | K3: Fórmulas de limpieza
A4: =Datos_Raw!A4 -> 45292 | B4: =YEAR(A4) -> 2024 | C4: =Datos_Raw!B4 -> Enero 2024 | D4: =PROPER(TRIM(Datos_Raw!C4)) -> Norte | E4: =PROPER(TRIM(Datos_Raw!D4)) -> Tecnologia | F4: =IFERROR(VALUE(TRIM(Datos_Raw!E4)),0) -> 17 | G4: =Datos_Raw!F4 -> 2600 | H4: =F4*G4 -> 44200 | I4: =IF(OR(D4="",E4="",F4<=0,G4<=0),"Revisar","OK") -> OK | K4: Region | L4: =PROPER(TRIM(Datos_Raw!C4)) -> Norte
A5: =Datos_Raw!A5 -> 45292 | B5: =YEAR(A5) -> 2024 | C5: =Datos_Raw!B5 -> Enero 2024 | D5: =PROPER(TRIM(Datos_Raw!C5)) -> Norte | E5: =PROPER(TRIM(Datos_Raw!D5)) -> Hogar | F5: =IFERROR(VALUE(TRIM(Datos_Raw!E5)),0) -> 21 | G5: =Datos_Raw!F5 -> 1500 | H5: =F5*G5 -> 31500 | I5: =IF(OR(D5="",E5="",F5<=0,G5<=0),"Revisar","OK") -> OK | K5: Categoria | L5: =PROPER(TRIM(Datos_Raw!D4)) -> Tecnologia
A6: =Datos_Raw!A6 -> 45292 | B6: =YEAR(A6) -> 2024 | C6: =Datos_Raw!B6 -> Enero 2024 | D6: =PROPER(TRIM(Datos_Raw!C6)) -> Norte | E6: =PROPER(TRIM(Datos_Raw!D6)) -> Oficina | F6: =IFERROR(VALUE(TRIM(Datos_Raw!E6)),0) -> 19 | G6: =Datos_Raw!F6 -> 1100 | H6: =F6*G6 -> 20900 | I6: =IF(OR(D6="",E6="",F6<=0,G6<=0),"Revisar","OK") -> OK | K6: Unidades | L6: =IFERROR(VALUE(TRIM(Datos_Raw!E4)),0) -> 17
A7: =Datos_Raw!A7 -> 45292 | B7: =YEAR(A7) -> 2024 | C7: =Datos_Raw!B7 -> Enero 2024 | D7: =PROPER(TRIM(Datos_Raw!C7)) -> Sur | E7: =PROPER(TRIM(Datos_Raw!D7)) -> Tecnologia | F7: =IFERROR(VALUE(TRIM(Datos_Raw!E7)),0) -> 14 | G7: =Datos_Raw!F7 -> 2600 | H7: =F7*G7 -> 36400 | I7: =IF(OR(D7="",E7="",F7<=0,G7<=0),"Revisar","OK") -> OK | K7: Ventas | L7: =F4*G4 -> 44200
A8: =Datos_Raw!A8 -> 45292 | B8: =YEAR(A8) -> 2024 | C8: =Datos_Raw!B8 -> Enero 2024 | D8: =PROPER(TRIM(Datos_Raw!C8)) -> Sur | E8: =PROPER(TRIM(Datos_Raw!D8)) -> Hogar | F8: =IFERROR(VALUE(TRIM(Datos_Raw!E8)),0) -> 18 | G8: =Datos_Raw!F8 -> 1500 | H8: =F8*G8 -> 27000 | I8: =IF(OR(D8="",E8="",F8<=0,G8<=0),"Revisar","OK") -> OK
A9: =Datos_Raw!A9 -> 45292 | B9: =YEAR(A9) -> 2024 | C9: =Datos_Raw!B9 -> Enero 2024 | D9: =PROPER(TRIM(Datos_Raw!C9)) -> Sur | E9: =PROPER(TRIM(Datos_Raw!D9)) -> Oficina | F9: =IFERROR(VALUE(TRIM(Datos_Raw!E9)),0) -> 16 | G9: =Datos_Raw!F9 -> 1100 | H9: =F9*G9 -> 17600 | I9: =IF(OR(D9="",E9="",F9<=0,G9<=0),"Revisar","OK") -> OK
A10: =Datos_Raw!A10 -> 45323 | B10: =YEAR(A10) -> 2024 | C10: =Datos_Raw!B10 -> Febrero 2024 | D10: =PROPER(TRIM(Datos_Raw!C10)) -> Norte | E10: =PROPER(TRIM(Datos_Raw!D10)) -> Tecnologia | F10: =IFERROR(VALUE(TRIM(Datos_Raw!E10)),0) -> 19 | G10: =Datos_Raw!F10 -> 2600 | H10: =F10*G10 -> 49400 | I10: =IF(OR(D10="",E10="",F10<=0,G10<=0),"Revisar","OK") -> OK
A11: =Datos_Raw!A11 -> 45323 | B11: =YEAR(A11) -> 2024 | C11: =Datos_Raw!B11 -> Febrero 2024 | D11: =PROPER(TRIM(Datos_Raw!C11)) -> Norte | E11: =PROPER(TRIM(Datos_Raw!D11)) -> Hogar | F11: =IFERROR(VALUE(TRIM(Datos_Raw!E11)),0) -> 24 | G11: =Datos_Raw!F11 -> 1500 | H11: =F11*G11 -> 36000 | I11: =IF(OR(D11="",E11="",F11<=0,G11<=0),"Revisar","OK") -> OK
A12: =Datos_Raw!A12 -> 45323 | B12: =YEAR(A12) -> 2024 | C12: =Datos_Raw!B12 -> Febrero 2024 | D12: =PROPER(TRIM(Datos_Raw!C12)) -> Norte | E12: =PROPER(TRIM(Datos_Raw!D12)) -> Oficina | F12: =IFERROR(VALUE(TRIM(Datos_Raw!E12)),0) -> 21 | G12: =Datos_Raw!F12 -> 1100 | H12: =F12*G12 -> 23100 | I12: =IF(OR(D12="",E12="",F12<=0,G12<=0),"Revisar","OK") -> OK
A13: =Datos_Raw!A13 -> 45323 | B13: =YEAR(A13) -> 2024 | C13: =Datos_Raw!B13 -> Febrero 2024 | D13: =PROPER(TRIM(Datos_Raw!C13)) -> Sur | E13: =PROPER(TRIM(Datos_Raw!D13)) -> Tecnologia | F13: =IFERROR(VALUE(TRIM(Datos_Raw!E13)),0) -> 16 | G13: =Datos_Raw!F13 -> 2600 | H13: =F13*G13 -> 41600 | I13: =IF(OR(D13="",E13="",F13<=0,G13<=0),"Revisar","OK") -> OK
A14: =Datos_Raw!A14 -> 45323 | B14: =YEAR(A14) -> 2024 | C14: =Datos_Raw!B14 -> Febrero 2024 | D14: =PROPER(TRIM(Datos_Raw!C14)) -> Sur | E14: =PROPER(TRIM(Datos_Raw!D14)) -> Hogar | F14: =IFERROR(VALUE(TRIM(Datos_Raw!E14)),0) -> 20 | G14: =Datos_Raw!F14 -> 1500 | H14: =F14*G14 -> 30000 | I14: =IF(OR(D14="",E14="",F14<=0,G14<=0),"Revisar","OK") -> OK
A15: =Datos_Raw!A15 -> 45323 | B15: =YEAR(A15) -> 2024 | C15: =Datos_Raw!B15 -> Febrero 2024 | D15: =PROPER(TRIM(Datos_Raw!C15)) -> Sur | E15: =PROPER(TRIM(Datos_Raw!D15)) -> Oficina | F15: =IFERROR(VALUE(TRIM(Datos_Raw!E15)),0) -> 18 | G15: =Datos_Raw!F15 -> 1100 | H15: =F15*G15 -> 19800 | I15: =IF(OR(D15="",E15="",F15<=0,G15<=0),"Revisar","OK") -> OK
A16: =Datos_Raw!A16 -> 45352 | B16: =YEAR(A16) -> 2024 | C16: =Datos_Raw!B16 -> Marzo 2024 | D16: =PROPER(TRIM(Datos_Raw!C16)) -> Norte | E16: =PROPER(TRIM(Datos_Raw!D16)) -> Tecnologia | F16: =IFERROR(VALUE(TRIM(Datos_Raw!E16)),0) -> 19 | G16: =Datos_Raw!F16 -> 2600 | H16: =F16*G16 -> 49400 | I16: =IF(OR(D16="",E16="",F16<=0,G16<=0),"Revisar","OK") -> OK
A17: =Datos_Raw!A17 -> 45352 | B17: =YEAR(A17) -> 2024 | C17: =Datos_Raw!B17 -> Marzo 2024 | D17: =PROPER(TRIM(Datos_Raw!C17)) -> Norte | E17: =PROPER(TRIM(Datos_Raw!D17)) -> Hogar | F17: =IFERROR(VALUE(TRIM(Datos_Raw!E17)),0) -> 24 | G17: =Datos_Raw!F17 -> 1500 | H17: =F17*G17 -> 36000 | I17: =IF(OR(D17="",E17="",F17<=0,G17<=0),"Revisar","OK") -> OK
A18: =Datos_Raw!A18 -> 45352 | B18: =YEAR(A18) -> 2024 | C18: =Datos_Raw!B18 -> Marzo 2024 | D18: =PROPER(TRIM(Datos_Raw!C18)) -> Norte | E18: =PROPER(TRIM(Datos_Raw!D18)) -> Oficina | F18: =IFERROR(VALUE(TRIM(Datos_Raw!E18)),0) -> 22 | G18: =Datos_Raw!F18 -> 1100 | H18: =F18*G18 -> 24200 | I18: =IF(OR(D18="",E18="",F18<=0,G18<=0),"Revisar","OK") -> OK
A19: =Datos_Raw!A19 -> 45352 | B19: =YEAR(A19) -> 2024 | C19: =Datos_Raw!B19 -> Marzo 2024 | D19: =PROPER(TRIM(Datos_Raw!C19)) -> Sur | E19: =PROPER(TRIM(Datos_Raw!D19)) -> Tecnologia | F19: =IFERROR(VALUE(TRIM(Datos_Raw!E19)),0) -> 16 | G19: =Datos_Raw!F19 -> 2600 | H19: =F19*G19 -> 41600 | I19: =IF(OR(D19="",E19="",F19<=0,G19<=0),"Revisar","OK") -> OK
... A75: =Datos_Raw!A75 -> 45627 | B75: =YEAR(A75) -> 2024 | C75: =Datos_Raw!B75 -> Diciembre 2024 | D75: =PROPER(TRIM(Datos_Raw!C75)) -> Sur | E75: =PROPER(TRIM(Datos_Raw!D75)) -> Oficina | F75: =IFERROR(VALUE(TRIM(Datos_Raw!E75)),0) -> 33 | G75: =Datos_Raw!F75 -> 1100 | H75: =F75*G75 -> 36300 | I75: =IF(OR(D75="",E75="",F75<=0,G75<=0),"Revisar","OK") -> OK

Sheet Dashboard
B2: Dashboard interactivo
B4: Filtro Región | C4: Norte | E4: Filtro Categoría | F4: Oficina
B6: Ventas filtradas | E6: Unidades filtradas | H6: Ticket promedio | K6: Registros analizados
B7: =SUMPRODUCT(--((Dashboard!$C$4="Todas")+(Datos_Limpios!$D$4:$D$75=Dashboard!$C$4)>0),--((Dashboard!$F$4="Todas")+(Datos_Limpios!$E$4:$E$75=Dashboard!$F$4)>0),Datos_Limpios!$H$4:$H$75) -> 383900 | E7: =SUMPRODUCT(--((Dashboard!$C$4="Todas")+(Datos_Limpios!$D$4:$D$75=Dashboard!$C$4)>0),--((Dashboard!$F$4="Todas")+(Datos_Limpios!$E$4:$E$75=Dashboard!$F$4)>0),Datos_Limpios!$F$4:$F$75) -> 349 | H7: =IF(E7=0,0,B7/E7) -> 1100 | K7: =SUMPRODUCT(--((Dashboard!$C$4="Todas")+(Datos_Limpios!$D$4:$D$75=Dashboard!$C$4)>0),--((Dashboard!$F$4="Todas")+(Datos_Limpios!$E$4:$E$75=Dashboard!$F$4)>0)) -> 12
B9: Visualización 1: tendencia mensual de ventas según los filtros activos. | F9: Visualización 2: comparación acumulada por categoría. Este gráfico ignora el filtro de categoría para permitir comparación. | J9: Visualización 3: comparación acumulada por región. Este gráfico ignora el filtro de región para permitir comparación.
A20: Mes | B20: Ventas | F20: Categoria | G20: Ventas | J20: Region | K20: Ventas
A21: Enero 2024 | B21: =SUMPRODUCT(--(Datos_Limpios!$C$4:$C$75=A21),--((Dashboard!$C$4="Todas")+(Datos_Limpios!$D$4:$D$75=Dashboard!$C$4)>0),--((Dashboard!$F$4="Todas")+(Datos_Limpios!$E$4:$E$75=Dashboard!$F$4)>0),Datos_Limpios!$H$4:$H$75) -> 20900 | F21: Tecnologia | G21: =SUMPRODUCT(--(Datos_Limpios!$E$4:$E$75=F21),--((Dashboard!$C$4="Todas")+(Datos_Limpios!$D$4:$D$75=Dashboard!$C$4)>0),Datos_Limpios!$H$4:$H$75) -> 837200 | J21: Norte | K21: =SUMPRODUCT(--(Datos_Limpios!$D$4:$D$75=J21),--((Dashboard!$F$4="Todas")+(Datos_Limpios!$E$4:$E$75=Dashboard!$F$4)>0),Datos_Limpios!$H$4:$H$75) -> 383900
A22: Febrero 2024 | B22: =SUMPRODUCT(--(Datos_Limpios!$C$4:$C$75=A22),--((Dashboard!$C$4="Todas")+(Datos_Limpios!$D$4:$D$75=Dashboard!$C$4)>0),--((Dashboard!$F$4="Todas")+(Datos_Limpios!$E$4:$E$75=Dashboard!$F$4)>0),Datos_Limpios!$H$4:$H$75) -> 23100 | F22: Hogar | G22: =SUMPRODUCT(--(Datos_Limpios!$E$4:$E$75=F22),--((Dashboard!$C$4="Todas")+(Datos_Limpios!$D$4:$D$75=Dashboard!$C$4)>0),Datos_Limpios!$H$4:$H$75) -> 562500 | J22: Sur | K22: =SUMPRODUCT(--(Datos_Limpios!$D$4:$D$75=J22),--((Dashboard!$F$4="Todas")+(Datos_Limpios!$E$4:$E$75=Dashboard!$F$4)>0),Datos_Limpios!$H$4:$H$75) -> 319000
A23: Marzo 2024 | B23: =SUMPRODUCT(--(Datos_Limpios!$C$4:$C$75=A23),--((Dashboard!$C$4="Todas")+(Datos_Limpios!$D$4:$D$75=Dashboard!$C$4)>0),--((Dashboard!$F$4="Todas")+(Datos_Limpios!$E$4:$E$75=Dashboard!$F$4)>0),Datos_Limpios!$H$4:$H$75) -> 24200 | F23: Oficina | G23: =SUMPRODUCT(--(Datos_Limpios!$E$4:$E$75=F23),--((Dashboard!$C$4="Todas")+(Datos_Limpios!$D$4:$D$75=Dashboard!$C$4)>0),Datos_Limpios!$H$4:$H$75) -> 383900
A24: Abril 2024 | B24: =SUMPRODUCT(--(Datos_Limpios!$C$4:$C$75=A24),--((Dashboard!$C$4="Todas")+(Datos_Limpios!$D$4:$D$75=Dashboard!$C$4)>0),--((Dashboard!$F$4="Todas")+(Datos_Limpios!$E$4:$E$75=Dashboard!$F$4)>0),Datos_Limpios!$H$4:$H$75) -> 27500
A25: Mayo 2024 | B25: =SUMPRODUCT(--(Datos_Limpios!$C$4:$C$75=A25),--((Dashboard!$C$4="Todas")+(Datos_Limpios!$D$4:$D$75=Dashboard!$C$4)>0),--((Dashboard!$F$4="Todas")+(Datos_Limpios!$E$4:$E$75=Dashboard!$F$4)>0),Datos_Limpios!$H$4:$H$75) -> 27500
A26: Junio 2024 | B26: =SUMPRODUCT(--(Datos_Limpios!$C$4:$C$75=A26),--((Dashboard!$C$4="Todas")+(Datos_Limpios!$D$4:$D$75=Dashboard!$C$4)>0),--((Dashboard!$F$4="Todas")+(Datos_Limpios!$E$4:$E$75=Dashboard!$F$4)>0),Datos_Limpios!$H$4:$H$75) -> 31900
A27: Julio 2024 | B27: =SUMPRODUCT(--(Datos_Limpios!$C$4:$C$75=A27),--((Dashboard!$C$4="Todas")+(Datos_Limpios!$D$4:$D$75=Dashboard!$C$4)>0),--((Dashboard!$F$4="Todas")+(Datos_Limpios!$E$4:$E$75=Dashboard!$F$4)>0),Datos_Limpios!$H$4:$H$75) -> 31900
A28: Agosto 2024 | B28: =SUMPRODUCT(--(Datos_Limpios!$C$4:$C$75=A28),--((Dashboard!$C$4="Todas")+(Datos_Limpios!$D$4:$D$75=Dashboard!$C$4)>0),--((Dashboard!$F$4="Todas")+(Datos_Limpios!$E$4:$E$75=Dashboard!$F$4)>0),Datos_Limpios!$H$4:$H$75) -> 36300
A29: Septiembre 2024 | B29: =SUMPRODUCT(--(Datos_Limpios!$C$4:$C$75=A29),--((Dashboard!$C$4="Todas")+(Datos_Limpios!$D$4:$D$75=Dashboard!$C$4)>0),--((Dashboard!$F$4="Todas")+(Datos_Limpios!$E$4:$E$75=Dashboard!$F$4)>0),Datos_Limpios!$H$4:$H$75) -> 36300
A30: Octubre 2024 | B30: =SUMPRODUCT(--(Datos_Limpios!$C$4:$C$75=A30),--((Dashboard!$C$4="Todas")+(Datos_Limpios!$D$4:$D$75=Dashboard!$C$4)>0),--((Dashboard!$F$4="Todas")+(Datos_Limpios!$E$4:$E$75=Dashboard!$F$4)>0),Datos_Limpios!$H$4:$H$75) -> 39600
A31: Noviembre 2024 | B31: =SUMPRODUCT(--(Datos_Limpios!$C$4:$C$75=A31),--((Dashboard!$C$4="Todas")+(Datos_Limpios!$D$4:$D$75=Dashboard!$C$4)>0),--((Dashboard!$F$4="Todas")+(Datos_Limpios!$E$4:$E$75=Dashboard!$F$4)>0),Datos_Limpios!$H$4:$H$75) -> 40700
A32: Diciembre 2024 | B32: =SUMPRODUCT(--(Datos_Limpios!$C$4:$C$75=A32),--((Dashboard!$C$4="Todas")+(Datos_Limpios!$D$4:$D$75=Dashboard!$C$4)>0),--((Dashboard!$F$4="Todas")+(Datos_Limpios!$E$4:$E$75=Dashboard!$F$4)>0),Datos_Limpios!$H$4:$H$75) -> 44000

Sheet Pronostico
B2: Proyección del próximo trimestre
B4: Se utiliza un modelo simple basado en el promedio de crecimiento de los últimos 6 meses para estimar los siguientes 3 meses.
B6: Mes | C6: Ventas reales | D6: Índice | E6: Variación mensual | G6: Promedio crecimiento últimos 6 meses | H6: =AVERAGE(E13:E18) -> 0.057975598
B7: Enero 2024 | C7: =SUMIF(Datos_Limpios!$C$4:$C$75,B7,Datos_Limpios!$H$4:$H$75) -> 177600 | D7: 1 | G7: Venta total 2024 | H7: =SUM(C7:C18) -> 3271500
B8: Febrero 2024 | C8: =SUMIF(Datos_Limpios!$C$4:$C$75,B8,Datos_Limpios!$H$4:$H$75) -> 199900 | D8: 2 | E8: =IFERROR(C8/C7-1,0) -> 0.12556306 | G8: Promedio mensual 2024 | H8: =AVERAGE(C7:C18) -> 272625
B9: Marzo 2024 | C9: =SUMIF(Datos_Limpios!$C$4:$C$75,B9,Datos_Limpios!$H$4:$H$75) -> 201000 | D9: 3 | E9: =IFERROR(C9/C8-1,0) -> 0.0055027514
B10: Abril 2024 | C10: =SUMIF(Datos_Limpios!$C$4:$C$75,B10,Datos_Limpios!$H$4:$H$75) -> 234800 | D10: 4 | E10: =IFERROR(C10/C9-1,0) -> 0.1681592 | G10: Mes con mayor proyección | H10: =INDEX(B21:B23,MATCH(MAX(C21:C23),C21:C23,0)) -> Marzo 2025
B11: Mayo 2024 | C11: =SUMIF(Datos_Limpios!$C$4:$C$75,B11,Datos_Limpios!$H$4:$H$75) -> 236300 | D11: 5 | E11: =IFERROR(C11/C10-1,0) -> 0.0063884157 | G11: Valor proyectado máximo | H11: =MAX(C21:C23) -> 447392.71
B12: Junio 2024 | C12: =SUMIF(Datos_Limpios!$C$4:$C$75,B12,Datos_Limpios!$H$4:$H$75) -> 271200 | D12: 6 | E12: =IFERROR(C12/C11-1,0) -> 0.14769361
B13: Julio 2024 | C13: =SUMIF(Datos_Limpios!$C$4:$C$75,B13,Datos_Limpios!$H$4:$H$75) -> 271200 | D13: 7 | E13: =IFERROR(C13/C12-1,0) -> 0
B14: Agosto 2024 | C14: =SUMIF(Datos_Limpios!$C$4:$C$75,B14,Datos_Limpios!$H$4:$H$75) -> 305000 | D14: 8 | E14: =IFERROR(C14/C13-1,0) -> 0.12463127
B15: Septiembre 2024 | C15: =SUMIF(Datos_Limpios!$C$4:$C$75,B15,Datos_Limpios!$H$4:$H$75) -> 310200 | D15: 9 | E15: =IFERROR(C15/C14-1,0) -> 0.01704918
B16: Octubre 2024 | C16: =SUMIF(Datos_Limpios!$C$4:$C$75,B16,Datos_Limpios!$H$4:$H$75) -> 341400 | D16: 10 | E16: =IFERROR(C16/C15-1,0) -> 0.10058027
B17: Noviembre 2024 | C17: =SUMIF(Datos_Limpios!$C$4:$C$75,B17,Datos_Limpios!$H$4:$H$75) -> 345100 | D17: 11 | E17: =IFERROR(C17/C16-1,0) -> 0.010837727
B18: Diciembre 2024 | C18: =SUMIF(Datos_Limpios!$C$4:$C$75,B18,Datos_Limpios!$H$4:$H$75) -> 377800 | D18: 12 | E18: =IFERROR(C18/C17-1,0) -> 0.094755143
B20: Mes proyectado | C20: Ventas proyectadas | D20: Índice
B21: Enero 2025 | C21: =$C$18*(1+$H$6) -> 399703.18 | D21: 13
B22: Febrero 2025 | C22: =C21*(1+$H$6) -> 422876.21 | D22: 14
B23: Marzo 2025 | C23: =C22*(1+$H$6) -> 447392.71 | D23: 15

Sheet Resumen
B2: Interpretación de resultados
B4: Pregunta clave | C4: ¿En qué mes se proyectan mayores ventas del próximo trimestre y qué categoría lidera el acumulado?
B7: Mes con mayor venta proyectada | C7: =Pronostico!H10 -> Marzo 2025 | H7: Categoria | I7: Ventas
H8: Tecnologia | I8: =SUMIF(Datos_Limpios!$E$4:$E$75,H8,Datos_Limpios!$H$4:$H$75) -> 1536600
H9: Hogar | I9: =SUMIF(Datos_Limpios!$E$4:$E$75,H9,Datos_Limpios!$H$4:$H$75) -> 1032000
B10: Valor proyectado máximo | C10: =Pronostico!H11 -> 447392.71 | H10: Oficina | I10: =SUMIF(Datos_Limpios!$E$4:$E$75,H10,Datos_Limpios!$H$4:$H$75) -> 702900
B13: Categoría líder acumulada | C13: =INDEX(H8:H10,MATCH(MAX(I8:I10),I8:I10,0)) -> Tecnologia | H13: Region | I13: Ventas
H14: Norte | I14: =SUMIF(Datos_Limpios!$D$4:$D$75,H14,Datos_Limpios!$H$4:$H$75) -> 1783600
H15: Sur | I15: =SUMIF(Datos_Limpios!$D$4:$D$75,H15,Datos_Limpios!$H$4:$H$75) -> 1487900
B16: Región líder acumulada | C16: =INDEX(H14:H15,MATCH(MAX(I14:I15),I14:I15,0)) -> Norte
B19: Ventas totales 2024 | C19: =SUM(Datos_Limpios!H4:H75) -> 3271500
B22: Promedio mensual 2024 | C22: =AVERAGE(Pronostico!C7:C18) -> 272625
B25: Hallazgo 1 | C25: La tendencia mensual de ventas es creciente durante 2024, lo que favorece una proyección ascendente del siguiente trimestre.
B27: Hallazgo 2 | C27: Tecnologia concentra el mayor aporte acumulado y Norte es la región con mejor desempeño total.
B29: Recomendación | C29: Planificar inventario y seguimiento comercial para el mes proyectado más fuerte, y priorizar campañas en la categoría líder.

Sheet Documentacion
B2: Documentación del proceso
B4: Problema y objetivo
B5: Problema | C5: Se requiere transformar una tabla sencilla de ventas en un dashboard que apoye decisiones y permita proyectar el siguiente trimestre.
B7: Objetivo | C7: Identificar el mes proyectado con mayores ventas y la categoría con mayor aporte acumulado.
B9: Limpieza y análisis
B10: Limpieza aplicada | C10: Estandarización de texto en Región y Categoría, conversión de Unidades a número y recálculo de Ventas.
B12: Análisis aplicado | C12: KPIs, tendencia mensual filtrable, comparación por categoría, comparación por región y proyección del próximo trimestre.
B14: Herramientas y fórmulas
B15: Excel | C15: Tablas, validaciones de lista, gráficos, SUMPRODUCT, SUMIF, INDEX+MATCH, AVERAGE, YEAR, IFERROR, TRIM y PROPER.
B17: IA complementaria | C17: Apoyo para definir la pregunta clave, proponer estructura del dashboard, redactar hallazgos y preparar el guion del video.
B19: Prompts usados con IA
B20: Prompt 1 | C20: Propón una estructura sencilla de dashboard en Excel para analizar ventas mensuales y proyectar el siguiente trimestre.
B22: Prompt 2 | C22: ¿Qué fórmulas de Excel sirven para limpiar textos con espacios, convertir cantidades y resumir ventas por filtros?
B24: Prompt 3 | C24: Ayúdame a redactar conclusiones cortas y un guion de video de 3 a 5 minutos para presentar el proyecto.
B26: Reflexión ética
B27: Uso responsable | C27: La IA se utilizó como apoyo para organizar ideas y mejorar la presentación, no para reemplazar la verificación de fórmulas ni la interpretación crítica.
B29: Límite importante | C29: La proyección es un modelo simple y no debe interpretarse como certeza absoluta; cualquier decisión real requiere validación adicional con datos históricos más amplios.

Sheet Listas
A1: Todas | B1: Todas | D1: Categoria | E1: Region
A2: Norte | B2: Tecnologia | D2: Tecnologia | E2: Norte
A3: Sur | B3: Hogar | D3: Hogar | E3: Sur
B4: Oficina | D4: Oficina
